{
  "iconSettings": {
    "channelIconSize": 22,
    "ytIconSize": 32
  },
  "savedTabs": [
    {
      "favicon": "https://www.youtube.com/s/desktop/6cd492c3/img/favicon_32x32.png",
      "id": 1769798537246,
      "savedAt": "2026-01-30T18:42:17.246Z",
      "title": "(351) ৫০তম বিসিএস এর সকল গুরুত্বপূর্ণ সাম্প্রতিক || Recent Issues || সমীক্ষা | যুদ্ধ | তারিখ | সংখ্যা - YouTube",
      "url": "https://www.youtube.com/watch?v=qHmnxPbfEPs"
    },
    {
      "favicon": "https://www.youtube.com/s/desktop/6cd492c3/img/favicon_32x32.png",
      "id": 1769798544633,
      "savedAt": "2026-01-30T18:42:24.633Z",
      "title": "(351) ৫০তম বিসিএস সাজেশনমূলক রিভিশন ক্লাস | BCS | Job - YouTube",
      "url": "https://www.youtube.com/watch?v=T_s19eTjfPY"
    },
    {
      "favicon": "https://ssl.gstatic.com/images/branding/product/1x/drive_2020q4_32dp.png",
      "id": 1769798610352,
      "savedAt": "2026-01-30T18:43:30.352Z",
      "title": "৫০তম বিসিএস সাম্প্রতিক ও চলমান ঘটনা প্রবাহ by Zahidul Islam BCS Intelligence.pdf - Google Drive",
      "url": "https://drive.google.com/file/d/1tCpclIhys3jGsOjnFZeyZyCZQOl_H_wB/view?pli=1"
    },
    {
      "favicon": "https://careericons.com/adminicon/images/icons/logo_icon.ico",
      "id": 1769798784585,
      "savedAt": "2026-01-30T18:46:24.585Z",
      "title": "Free General english Live Quiz For All Competitive Exam Preparations",
      "url": "https://careericons.com/free-online-test/general-english-mcq/"
    },
    {
      "channelIcon": "https://yt3.ggpht.com/_Q8DnNm6nXHjLtNGWuhMlvqt1G9BilcflliJv28jFQcsjtUtfUWvRo6FNTWkhRXno84QkJOPQw=s48-c-k-c0x00ffffff-no-rj",
      "favicon": "https://www.youtube.com/s/desktop/6cd492c3/img/favicon_32x32.png",
      "id": 1769973444641,
      "savedAt": "2026-02-01T19:17:24.641Z",
      "title": "(381) Crazy Hand Trick to Find Exact Trigonometric Values - YouTube",
      "url": "https://www.youtube.com/watch?v=1RJ-DIwxdqQ"
    },
    {
      "channelIcon": "https://yt3.ggpht.com/ytc/AIdro_k9yk3C75fsp_rAEzm5hBlYyjBTJ148-R0HrC6x6t-AEVc=s48-c-k-c0x00ffffff-no-rj",
      "favicon": "https://www.youtube.com/s/desktop/6cd492c3/img/favicon_32x32.png",
      "id": 1770215715133,
      "savedAt": "2026-02-04T14:35:15.133Z",
      "title": "(429) Current Affairs February 2026 Job Admission preparation Update Gk কারেন্ট অ্যাফেয়ার্স Myclassroom - YouTube",
      "url": "https://www.youtube.com/watch?v=g71BRzkZQ8I"
    },
    {
      "channelIcon": "https://yt3.ggpht.com/ytc/AIdro_k9yk3C75fsp_rAEzm5hBlYyjBTJ148-R0HrC6x6t-AEVc=s48-c-k-c0x00ffffff-no-rj",
      "favicon": "https://www.youtube.com/s/desktop/ff2287a3/img/favicon_32x32.png",
      "id": 1770258218325,
      "savedAt": "2026-02-05T02:23:38.325Z",
      "title": "(436) বাংলা সাহিত্য থেকে গুরুত্বপূর্ন প্রশ্নোত্তর। চাকরি পরীক্ষা প্রশ্ন সমাধান। Job Preparation #gk - YouTube",
      "url": "https://www.youtube.com/watch?v=WpkT1vmCs5Y"
    },
    {
      "channelIcon": "https://yt3.ggpht.com/ioZ2TWSKx7qythilPMaVhxo7843Ts4Lc6d4TV5Dc9sflhM_hZNxvjaxg8lCfBQr21ChkmiN8VA=s48-c-k-c0x00ffffff-no-rj",
      "favicon": "https://www.youtube.com/s/desktop/2a3cb36e/img/favicon_32x32.png",
      "id": 1770718039839,
      "savedAt": "2026-02-10T10:07:19.839Z",
      "title": "(519) Tense & Conditional Sentence || আর কখনো ভুল হবে না || Sumon Sir || #turningpointjobaid - YouTube",
      "url": "https://www.youtube.com/watch?v=oa1YLuiTJfw"
    },
    {
      "channelIcon": "https://yt3.ggpht.com/ytc/AIdro_k9yk3C75fsp_rAEzm5hBlYyjBTJ148-R0HrC6x6t-AEVc=s48-c-k-c0x00ffffff-no-rj",
      "favicon": "https://www.youtube.com/s/desktop/2a3cb36e/img/favicon_32x32.png",
      "id": 1770719745351,
      "savedAt": "2026-02-10T10:35:45.351Z",
      "title": "(521) Current Affairs সাম্প্রতিক সাধারন জ্ঞান 39টি কমন প্রশ্নোত্তর। BCS Primary Job Preparation gk - YouTube",
      "url": "https://www.youtube.com/watch?v=Wn-6_erhhf8"
    },
    {
      "channelIcon": "https://yt3.ggpht.com/b5nasffRKpVbTHBMvGV8o1mdaRcg3FAzMuriJdCAtKkxfG1iHFo8VDAmLBbIp8Uya3ZZh8JC3g=s48-c-k-c0x00ffffff-no-rj",
      "favicon": "https://www.youtube.com/s/desktop/78e11dee/img/favicon_32x32.png",
      "id": 1771052879540,
      "savedAt": "2026-02-14T07:07:59.540Z",
      "title": "(25) Animal Sounds for Children (20 Amazing Animals) - YouTube",
      "url": "https://www.youtube.com/watch?v=h8Q-jlHBcXM"
    },
    {
      "channelIcon": "https://yt3.ggpht.com/ioZ2TWSKx7qythilPMaVhxo7843Ts4Lc6d4TV5Dc9sflhM_hZNxvjaxg8lCfBQr21ChkmiN8VA=s48-c-k-c0x00ffffff-no-rj",
      "favicon": "https://www.youtube.com/s/desktop/18bfd1c0/img/favicon_32x32.png",
      "id": 1772378895399,
      "savedAt": "2026-03-01T15:28:15.399Z",
      "title": "(20) এক ক্লাসে Geometry শেখার সহজ কৌশল || Easy strategy to learn Geometry in one class || Shuvro Sir - YouTube",
      "url": "https://www.youtube.com/watch?v=WIWYw4JfdZ8"
    },
    {
      "channelIcon": "https://yt3.ggpht.com/ioZ2TWSKx7qythilPMaVhxo7843Ts4Lc6d4TV5Dc9sflhM_hZNxvjaxg8lCfBQr21ChkmiN8VA=s48-c-k-c0x00ffffff-no-rj",
      "favicon": "https://www.youtube.com/s/desktop/ce9675e8/img/favicon_32x32.png",
      "id": 1772707439694,
      "savedAt": "2026-03-05T10:43:59.694Z",
      "title": "(47) Bangladesh Bank AD Preparation || কাজী নজরুল ইসলামের জীবনী || #turningpointjobaid - YouTube",
      "url": "https://www.youtube.com/watch?v=K88dQT63JEA"
    },
    {
      "channelIcon": "https://yt3.ggpht.com/ytc/AIdro_k9yk3C75fsp_rAEzm5hBlYyjBTJ148-R0HrC6x6t-AEVc=s48-c-k-c0x00ffffff-no-rj",
      "favicon": "https://www.youtube.com/s/desktop/ab5c3a01/img/favicon_32x32.png",
      "id": 1772967637245,
      "savedAt": "2026-03-08T11:00:37.245Z",
      "title": "(106) সাম্প্রতিক গুরুত্বপূর্ন সাধারন জ্ঞান প্রশ্নোত্তর। Current Affairs। চাকরি ও ভর্তি পরীক্ষা প্রস্তুতি - YouTube",
      "url": "https://www.youtube.com/watch?v=PLF6FE_YeZA"
    },
    {
      "channelIcon": "https://yt3.ggpht.com/J1lYQUcY-T1Wg9kQYk_u2aXV5r2QKg4p1JrC00YKYjnIz77QLC1wAT8FXjUMC4-CaoLmgkgV-w=s48-c-k-c0x00ffffff-no-rj",
      "favicon": "https://www.youtube.com/s/desktop/ab5c3a01/img/favicon_32x32.png",
      "id": 1772967655254,
      "savedAt": "2026-03-08T11:00:55.254Z",
      "title": "(106) Recent General Knowledge 2026 || সাম্প্রতিক সাধারণ জ্ঞান ২০২৬ থেকে ২০০টি এমসিকিউ - YouTube",
      "url": "https://www.youtube.com/watch?v=AZZ0YlAZQts"
    }
  ]
}