{
    "676915": {
        "id": "676915",
        "href": "/676915/kr-spark-vs-bestia-challengers-2026-latam-south-ace-stage-2-w4",
        "team1": "KRÜ SPARK",
        "team2": "BESTIA",
        "team1_logo": "/static/images_cache/69cfd386538cf.png",
        "team2_logo": "/static/images_cache/69ea66a9d008c.png",
        "tournament": "Challengers 2026: LATAM South ACE Stage 2",
        "tournament_logo": "/static/images_cache/63cbac52cf906.png",
        "series": "Group Stage–Week 4",
        "unix_timestamp": 1781722800,
        "bst_time": "2026-06-18 01:00 AM",
        "status": "Upcoming",
        "score1": "–",
        "score2": "–",
        "last_updated": 1781716704
    },
    "681928": {
        "id": "681928",
        "href": "/681928/tbk-esports-vs-tribe-challengers-2026-brazil-gamers-club-stage-2-w7",
        "team1": "TBK Esports",
        "team2": "TRIBE",
        "team1_logo": "/static/images_cache/61d39894f3d3a.png",
        "team2_logo": "/static/images_cache/6a1d05ea56fcb.png",
        "tournament": "Challengers 2026: Brazil Gamers Club Stage 2",
        "tournament_logo": "/static/images_cache/66203e302897c.png",
        "series": "Regular Phase–Week 7",
        "unix_timestamp": 1781726400,
        "bst_time": "2026-06-18 02:00 AM",
        "status": "Upcoming",
        "score1": "–",
        "score2": "–",
        "last_updated": 1781716704
    },
    "681930": {
        "id": "681930",
        "href": "/681930/mibr-academy-vs-f4tality-challengers-2026-brazil-gamers-club-stage-2-w7",
        "team1": "MIBR Academy",
        "team2": "F4TALITY",
        "team1_logo": "/static/images_cache/67127fdb2ae3e.png",
        "team2_logo": "/static/images_cache/6881cff4883f1.png",
        "tournament": "Challengers 2026: Brazil Gamers Club Stage 2",
        "tournament_logo": "/static/images_cache/66203e302897c.png",
        "series": "Regular Phase–Week 7",
        "unix_timestamp": 1781726400,
        "bst_time": "2026-06-18 02:00 AM",
        "status": "Upcoming",
        "score1": "–",
        "score2": "–",
        "last_updated": 1781716704
    },
    "688228": {
        "id": "688228",
        "href": "/688228/division-one-vs-evictix-challengers-2026-north-america-ace-stage-3-r4-1-2",
        "team1": "Division One",
        "team2": "Evictix",
        "team1_logo": "/static/images_cache/69da93c726b68.png",
        "team2_logo": "/static/images_cache/6a32243d7f7df.png",
        "tournament": "Challengers 2026: North America ACE Stage 3",
        "tournament_logo": "/static/images_cache/63cbac52cf906.png",
        "series": "Swiss Stage–Round 4 (1-2)",
        "unix_timestamp": 1781726400,
        "bst_time": "2026-06-18 02:00 AM",
        "status": "Upcoming",
        "score1": "–",
        "score2": "–",
        "last_updated": 1781716704
    },
    "688229": {
        "id": "688229",
        "href": "/688229/alliance-guardians-vs-pigeons-challengers-2026-north-america-ace-stage-3-r4-1-2",
        "team1": "Alliance Guardians",
        "team2": "Pigeons",
        "team1_logo": "/static/images_cache/698d499d024ef.png",
        "team2_logo": "/static/images_cache/68514906c5b54.png",
        "tournament": "Challengers 2026: North America ACE Stage 3",
        "tournament_logo": "/static/images_cache/63cbac52cf906.png",
        "series": "Swiss Stage–Round 4 (1-2)",
        "unix_timestamp": 1781726400,
        "bst_time": "2026-06-18 02:00 AM",
        "status": "Upcoming",
        "score1": "–",
        "score2": "–",
        "last_updated": 1781716704
    },
    "676916": {
        "id": "676916",
        "href": "/676916/university-war-vs-kr-blaze-challengers-2026-latam-south-ace-stage-2-w4",
        "team1": "University War",
        "team2": "KRÜ BLAZE",
        "team1_logo": "/static/images_cache/65df25f7afcad.png",
        "team2_logo": "/static/images_cache/6704ad6a515a1.png",
        "tournament": "Challengers 2026: LATAM South ACE Stage 2",
        "tournament_logo": "/static/images_cache/63cbac52cf906.png",
        "series": "Group Stage–Week 4",
        "unix_timestamp": 1781733600,
        "bst_time": "2026-06-18 04:00 AM",
        "status": "Upcoming",
        "score1": "–",
        "score2": "–",
        "last_updated": 1781716704
    },
    "678050": {
        "id": "678050",
        "href": "/678050/streamer-arena-vs-fusion-challengers-2026-latam-north-ace-stage-2-w4",
        "team1": "STREAMER ARENA",
        "team2": "FUSION",
        "team1_logo": "/static/images_cache/69c4c2382b847.png",
        "team2_logo": "/static/images_cache/63bde15e27452.png",
        "tournament": "Challengers 2026: LATAM North ACE Stage 2",
        "tournament_logo": "/static/images_cache/63cbac52cf906.png",
        "series": "Group Stage–Week 4",
        "unix_timestamp": 1781733600,
        "bst_time": "2026-06-18 04:00 AM",
        "status": "Upcoming",
        "score1": "–",
        "score2": "–",
        "last_updated": 1781716704
    },
    "681932": {
        "id": "681932",
        "href": "/681932/furia-academy-vs-peek-challengers-2026-brazil-gamers-club-stage-2-w7",
        "team1": "FURIA Academy",
        "team2": "PEEK",
        "team1_logo": "/static/images_cache/67a18f336c9f4.png",
        "team2_logo": "/static/images_cache/6918ed7fe1107.png",
        "tournament": "Challengers 2026: Brazil Gamers Club Stage 2",
        "tournament_logo": "/static/images_cache/66203e302897c.png",
        "series": "Regular Phase–Week 7",
        "unix_timestamp": 1781737200,
        "bst_time": "2026-06-18 05:00 AM",
        "status": "Upcoming",
        "score1": "–",
        "score2": "–",
        "last_updated": 1781716704
    },
    "688230": {
        "id": "688230",
        "href": "/688230/dynamo-vs-rose-challengers-2026-north-america-ace-stage-3-r4-0-3",
        "team1": "Dynamo",
        "team2": "ROSE",
        "team1_logo": "/static/images_cache/688474d4cebab.png",
        "team2_logo": "/static/images_cache/63ceb7850f650.png",
        "tournament": "Challengers 2026: North America ACE Stage 3",
        "tournament_logo": "/static/images_cache/63cbac52cf906.png",
        "series": "Swiss Stage–Round 4 (0-3)",
        "unix_timestamp": 1781737200,
        "bst_time": "2026-06-18 05:00 AM",
        "status": "Upcoming",
        "score1": "–",
        "score2": "–",
        "last_updated": 1781716704
    },
    "688231": {
        "id": "688231",
        "href": "/688231/flyquest-vs-evil-geniuses-academy-challengers-2026-north-america-ace-stage-3-r4-1-2",
        "team1": "FlyQuest",
        "team2": "Evil Geniuses Academy",
        "team1_logo": "/static/images_cache/69cac541ed59b.png",
        "team2_logo": "/static/images_cache/667462f046618.png",
        "tournament": "Challengers 2026: North America ACE Stage 3",
        "tournament_logo": "/static/images_cache/63cbac52cf906.png",
        "series": "Swiss Stage–Round 4 (1-2)",
        "unix_timestamp": 1781737200,
        "bst_time": "2026-06-18 05:00 AM",
        "status": "Upcoming",
        "score1": "–",
        "score2": "–",
        "last_updated": 1781716704
    },
    "678051": {
        "id": "678051",
        "href": "/678051/chivas-esports-vs-lyon-challengers-2026-latam-north-ace-stage-2-w4",
        "team1": "Chivas Esports",
        "team2": "LYON",
        "team1_logo": "/static/images_cache/63ce2eedbe573.png",
        "team2_logo": "/static/images_cache/6961e1fe322bd.png",
        "tournament": "Challengers 2026: LATAM North ACE Stage 2",
        "tournament_logo": "/static/images_cache/63cbac52cf906.png",
        "series": "Group Stage–Week 4",
        "unix_timestamp": 1781744400,
        "bst_time": "2026-06-18 07:00 AM",
        "status": "Upcoming",
        "score1": "–",
        "score2": "–",
        "last_updated": 1781716704
    },
    "686194": {
        "id": "686194",
        "href": "/686194/x-cast-vs-arete-challengers-2026-korea-wdg-split-2-w2",
        "team1": "X-CAST",
        "team2": "ARETE",
        "team1_logo": "/img/vlr/tmp/vlr.png",
        "team2_logo": "/static/images_cache/6980ab92813f2.png",
        "tournament": "Challengers 2026: Korea WDG Split 2",
        "tournament_logo": "/static/images_cache/6964a9e385d88.png",
        "series": "Group Stage–Week 2",
        "unix_timestamp": 1781769600,
        "bst_time": "2026-06-18 02:00 PM",
        "status": "Upcoming",
        "score1": "–",
        "score2": "–",
        "last_updated": 1781716704
    },
    "684635": {
        "id": "684635",
        "href": "/684635/fancy-united-esports-vs-trinity-challengers-2026-southeast-asia-split-2-lr2",
        "team1": "Fancy United Esports",
        "team2": "Trinity",
        "team1_logo": "/static/images_cache/697f25edef1f7.png",
        "team2_logo": "/static/images_cache/698c77f5ed4d3.png",
        "tournament": "Challengers 2026: Southeast Asia Split 2",
        "tournament_logo": "/static/images_cache/6964a9e385d88.png",
        "series": "Playoffs–Lower Round 2",
        "unix_timestamp": 1781780400,
        "bst_time": "2026-06-18 05:00 PM",
        "status": "Upcoming",
        "score1": "–",
        "score2": "–",
        "last_updated": 1781716704
    },
    "686195": {
        "id": "686195",
        "href": "/686195/drx-academy-vs-t1-academy-challengers-2026-korea-wdg-split-2-w2",
        "team1": "DRX Academy",
        "team2": "T1 Academy",
        "team1_logo": "/static/images_cache/63b17abd77fc0.png",
        "team2_logo": "/static/images_cache/5ea85d21e625f.png",
        "tournament": "Challengers 2026: Korea WDG Split 2",
        "tournament_logo": "/static/images_cache/6964a9e385d88.png",
        "series": "Group Stage–Week 2",
        "unix_timestamp": 1781780400,
        "bst_time": "2026-06-18 05:00 PM",
        "status": "Upcoming",
        "score1": "–",
        "score2": "–",
        "last_updated": 1781716704
    },
    "684636": {
        "id": "684636",
        "href": "/684636/555-vs-oasis-gaming-challengers-2026-southeast-asia-split-2-lr2",
        "team1": "555",
        "team2": "Oasis Gaming",
        "team1_logo": "/img/vlr/tmp/vlr.png",
        "team2_logo": "/static/images_cache/629f15187dd71.png",
        "tournament": "Challengers 2026: Southeast Asia Split 2",
        "tournament_logo": "/static/images_cache/6964a9e385d88.png",
        "series": "Playoffs–Lower Round 2",
        "unix_timestamp": 1781787600,
        "bst_time": "2026-06-18 07:00 PM",
        "status": "Upcoming",
        "score1": "–",
        "score2": "–",
        "last_updated": 1781716704
    },
    "676917": {
        "id": "676917",
        "href": "/676917/9z-globant-vs-oxen-challengers-2026-latam-south-ace-stage-2-w4",
        "team1": "9z Globant",
        "team2": "OXEN",
        "team1_logo": "/static/images_cache/65e447b0c2415.png",
        "team2_logo": "/static/images_cache/62cdc31a970d0.png",
        "tournament": "Challengers 2026: LATAM South ACE Stage 2",
        "tournament_logo": "/static/images_cache/63cbac52cf906.png",
        "series": "Group Stage–Week 4",
        "unix_timestamp": 1781809200,
        "bst_time": "2026-06-19 01:00 AM",
        "status": "Upcoming",
        "score1": "–",
        "score2": "–",
        "last_updated": 1781716704
    },
    "681931": {
        "id": "681931",
        "href": "/681931/intz-vs-team-ego-challengers-2026-brazil-gamers-club-stage-2-w7",
        "team1": "INTZ",
        "team2": "TEAM EGO",
        "team1_logo": "/static/images_cache/5fb3183339579.png",
        "team2_logo": "/img/vlr/tmp/vlr.png",
        "tournament": "Challengers 2026: Brazil Gamers Club Stage 2",
        "tournament_logo": "/static/images_cache/66203e302897c.png",
        "series": "Regular Phase–Week 7",
        "unix_timestamp": 1781812800,
        "bst_time": "2026-06-19 02:00 AM",
        "status": "Upcoming",
        "score1": "–",
        "score2": "–",
        "last_updated": 1781716704
    },
    "681933": {
        "id": "681933",
        "href": "/681933/elevate-vs-team-liquid-brazil-challengers-2026-brazil-gamers-club-stage-2-w7",
        "team1": "ELEVATE",
        "team2": "Team Liquid Brazil",
        "team1_logo": "/static/images_cache/65990c8ab7c2b.png",
        "team2_logo": "/static/images_cache/640c381f0603f.png",
        "tournament": "Challengers 2026: Brazil Gamers Club Stage 2",
        "tournament_logo": "/static/images_cache/66203e302897c.png",
        "series": "Regular Phase–Week 7",
        "unix_timestamp": 1781812800,
        "bst_time": "2026-06-19 02:00 AM",
        "status": "Upcoming",
        "score1": "–",
        "score2": "–",
        "last_updated": 1781716704
    },
    "688232": {
        "id": "688232",
        "href": "/688232/nightblood-gaming-vs-qor-challengers-2026-north-america-ace-stage-3-r4-2-1",
        "team1": "Nightblood Gaming",
        "team2": "QoR",
        "team1_logo": "/static/images_cache/61f13e1258cab.png",
        "team2_logo": "/static/images_cache/63e9a11797f41.png",
        "tournament": "Challengers 2026: North America ACE Stage 3",
        "tournament_logo": "/static/images_cache/63cbac52cf906.png",
        "series": "Swiss Stage–Round 4 (2-1)",
        "unix_timestamp": 1781812800,
        "bst_time": "2026-06-19 02:00 AM",
        "status": "Upcoming",
        "score1": "–",
        "score2": "–",
        "last_updated": 1781716704
    },
    "688233": {
        "id": "688233",
        "href": "/688233/shopify-rebellion-black-vs-azure-dragon-gaming-challengers-2026-north-america-ace-stage-3-r4-2",
        "team1": "Shopify Rebellion Black",
        "team2": "Azure Dragon Gaming",
        "team1_logo": "/static/images_cache/679314c8ac387.png",
        "team2_logo": "/static/images_cache/6a12ac6513cbe.png",
        "tournament": "Challengers 2026: North America ACE Stage 3",
        "tournament_logo": "/static/images_cache/63cbac52cf906.png",
        "series": "Swiss Stage–Round 4 (2-1)",
        "unix_timestamp": 1781812800,
        "bst_time": "2026-06-19 02:00 AM",
        "status": "Upcoming",
        "score1": "–",
        "score2": "–",
        "last_updated": 1781716704
    },
    "676918": {
        "id": "676918",
        "href": "/676918/leviat-n-academy-vs-shinden-challengers-2026-latam-south-ace-stage-2-w4",
        "team1": "LEVIATÁN Academy",
        "team2": "ShindeN",
        "team1_logo": "/static/images_cache/61b8888cc3860.png",
        "team2_logo": "/static/images_cache/6748dec4df18c.png",
        "tournament": "Challengers 2026: LATAM South ACE Stage 2",
        "tournament_logo": "/static/images_cache/63cbac52cf906.png",
        "series": "Group Stage–Week 4",
        "unix_timestamp": 1781820000,
        "bst_time": "2026-06-19 04:00 AM",
        "status": "Upcoming",
        "score1": "–",
        "score2": "–",
        "last_updated": 1781716704
    },
    "678052": {
        "id": "678052",
        "href": "/678052/fuego-vs-contra-challengers-2026-latam-north-ace-stage-2-w4",
        "team1": "FUEGO",
        "team2": "Contra",
        "team1_logo": "/static/images_cache/678f90b7b65e5.png",
        "team2_logo": "/static/images_cache/66572b1da4d79.png",
        "tournament": "Challengers 2026: LATAM North ACE Stage 2",
        "tournament_logo": "/static/images_cache/63cbac52cf906.png",
        "series": "Group Stage–Week 4",
        "unix_timestamp": 1781820000,
        "bst_time": "2026-06-19 04:00 AM",
        "status": "Upcoming",
        "score1": "–",
        "score2": "–",
        "last_updated": 1781716704
    },
    "681934": {
        "id": "681934",
        "href": "/681934/red-canids-vs-la-masia-challengers-2026-brazil-gamers-club-stage-2-w7",
        "team1": "RED Canids",
        "team2": "LA MASIA",
        "team1_logo": "/static/images_cache/63876c258b1e3.png",
        "team2_logo": "/img/vlr/tmp/vlr.png",
        "tournament": "Challengers 2026: Brazil Gamers Club Stage 2",
        "tournament_logo": "/static/images_cache/66203e302897c.png",
        "series": "Regular Phase–Week 7",
        "unix_timestamp": 1781823600,
        "bst_time": "2026-06-19 05:00 AM",
        "status": "Upcoming",
        "score1": "–",
        "score2": "–",
        "last_updated": 1781716704
    },
    "688234": {
        "id": "688234",
        "href": "/688234/m80-vs-sad-esports-challengers-2026-north-america-ace-stage-3-r4-3-0",
        "team1": "M80",
        "team2": "SaD Esports",
        "team1_logo": "/static/images_cache/6945c73504452.png",
        "team2_logo": "/static/images_cache/6528e9505cb61.png",
        "tournament": "Challengers 2026: North America ACE Stage 3",
        "tournament_logo": "/static/images_cache/63cbac52cf906.png",
        "series": "Swiss Stage–Round 4 (3-0)",
        "unix_timestamp": 1781823600,
        "bst_time": "2026-06-19 05:00 AM",
        "status": "Upcoming",
        "score1": "–",
        "score2": "–",
        "last_updated": 1781716704
    },
    "688235": {
        "id": "688235",
        "href": "/688235/yft-vs-nrg-academy-challengers-2026-north-america-ace-stage-3-r4-2-1",
        "team1": "YFT",
        "team2": "NRG Academy",
        "team1_logo": "/static/images_cache/6a1e4c6d6db88.png",
        "team2_logo": "/static/images_cache/6610f026c1a9e.png",
        "tournament": "Challengers 2026: North America ACE Stage 3",
        "tournament_logo": "/static/images_cache/63cbac52cf906.png",
        "series": "Swiss Stage–Round 4 (2-1)",
        "unix_timestamp": 1781823600,
        "bst_time": "2026-06-19 05:00 AM",
        "status": "Upcoming",
        "score1": "–",
        "score2": "–",
        "last_updated": 1781716704
    },
    "678053": {
        "id": "678053",
        "href": "/678053/ab3-esports-vs-lazer-challengers-2026-latam-north-ace-stage-2-w4",
        "team1": "AB3 Esports",
        "team2": "LAZER",
        "team1_logo": "/static/images_cache/679061092d445.png",
        "team2_logo": "/static/images_cache/698051cea67f9.png",
        "tournament": "Challengers 2026: LATAM North ACE Stage 2",
        "tournament_logo": "/static/images_cache/63cbac52cf906.png",
        "series": "Group Stage–Week 4",
        "unix_timestamp": 1781830800,
        "bst_time": "2026-06-19 07:00 AM",
        "status": "Upcoming",
        "score1": "–",
        "score2": "–",
        "last_updated": 1781716704
    },
    "670470": {
        "id": "670470",
        "href": "/670470/edward-gaming-vs-paper-rex-valorant-masters-london-2026-ubf",
        "team1": "EDward Gaming",
        "team2": "Paper Rex",
        "team1_logo": "/static/images_cache/62c82049253b2.png",
        "team2_logo": "/static/images_cache/62bbeba74d5cb.png",
        "tournament": "Valorant Masters London 2026",
        "tournament_logo": "/static/images_cache/692fc18a04f4a.png",
        "series": "Playoffs–Upper Final",
        "unix_timestamp": 1781874000,
        "bst_time": "2026-06-19 07:00 PM",
        "status": "Upcoming",
        "score1": "–",
        "score2": "–",
        "last_updated": 1781716704
    },
    "670476": {
        "id": "670476",
        "href": "/670476/team-vitality-vs-leviat-n-valorant-masters-london-2026-lr3",
        "team1": "Team Vitality",
        "team2": "LEVIATÁN",
        "team1_logo": "/static/images_cache/6466d79e1ed40.png",
        "team2_logo": "/static/images_cache/61b8888cc3860.png",
        "tournament": "Valorant Masters London 2026",
        "tournament_logo": "/static/images_cache/692fc18a04f4a.png",
        "series": "Playoffs–Lower Round 3",
        "unix_timestamp": 1781884800,
        "bst_time": "2026-06-19 10:00 PM",
        "status": "Upcoming",
        "score1": "–",
        "score2": "–",
        "last_updated": 1781716704
    },
    "693509": {
        "id": "693509",
        "href": "/693509/tbd-fortress-touch-grassroots-esports-2026-regional-finals-ubf",
        "team1": "TBD",
        "team2": "TBD",
        "team1_logo": "/img/vlr/tmp/vlr.png",
        "team2_logo": "/img/vlr/tmp/vlr.png",
        "tournament": "Fortress (touch)Grassroots Esports 2026: Regional Finals",
        "tournament_logo": "/static/images_cache/681eeaf6b7202.png",
        "series": "Playoffs–Upper Final",
        "unix_timestamp": 1781931600,
        "bst_time": "2026-06-20 11:00 AM",
        "status": "Upcoming",
        "score1": "–",
        "score2": "–",
        "last_updated": 1781716704
    },
    "693511": {
        "id": "693511",
        "href": "/693511/tbd-fortress-touch-grassroots-esports-2026-regional-finals-lr1",
        "team1": "TBD",
        "team2": "TBD",
        "team1_logo": "/img/vlr/tmp/vlr.png",
        "team2_logo": "/img/vlr/tmp/vlr.png",
        "tournament": "Fortress (touch)Grassroots Esports 2026: Regional Finals",
        "tournament_logo": "/static/images_cache/681eeaf6b7202.png",
        "series": "Playoffs–Lower Round 1",
        "unix_timestamp": 1781931600,
        "bst_time": "2026-06-20 11:00 AM",
        "status": "Upcoming",
        "score1": "–",
        "score2": "–",
        "last_updated": 1781716704
    },
    "693512": {
        "id": "693512",
        "href": "/693512/tbd-fortress-touch-grassroots-esports-2026-regional-finals-lbf",
        "team1": "TBD",
        "team2": "TBD",
        "team1_logo": "/img/vlr/tmp/vlr.png",
        "team2_logo": "/img/vlr/tmp/vlr.png",
        "tournament": "Fortress (touch)Grassroots Esports 2026: Regional Finals",
        "tournament_logo": "/static/images_cache/681eeaf6b7202.png",
        "series": "Playoffs–Lower Final",
        "unix_timestamp": 1781942400,
        "bst_time": "2026-06-20 02:00 PM",
        "status": "Upcoming",
        "score1": "–",
        "score2": "–",
        "last_updated": 1781716704
    },
    "670477": {
        "id": "670477",
        "href": "/670477/tbd-valorant-masters-london-2026-lbf",
        "team1": "TBD",
        "team2": "TBD",
        "team1_logo": "/img/vlr/tmp/vlr.png",
        "team2_logo": "/img/vlr/tmp/vlr.png",
        "tournament": "Valorant Masters London 2026",
        "tournament_logo": "/static/images_cache/692fc18a04f4a.png",
        "series": "Playoffs–Lower Final",
        "unix_timestamp": 1781960400,
        "bst_time": "2026-06-20 07:00 PM",
        "status": "Upcoming",
        "score1": "–",
        "score2": "–",
        "last_updated": 1781716704
    },
    "693510": {
        "id": "693510",
        "href": "/693510/tbd-fortress-touch-grassroots-esports-2026-regional-finals-gf",
        "team1": "TBD",
        "team2": "TBD",
        "team1_logo": "/img/vlr/tmp/vlr.png",
        "team2_logo": "/img/vlr/tmp/vlr.png",
        "tournament": "Fortress (touch)Grassroots Esports 2026: Regional Finals",
        "tournament_logo": "/static/images_cache/681eeaf6b7202.png",
        "series": "Playoffs–Grand Final",
        "unix_timestamp": 1782010800,
        "bst_time": "2026-06-21 09:00 AM",
        "status": "Upcoming",
        "score1": "–",
        "score2": "–",
        "last_updated": 1781716704
    },
    "670471": {
        "id": "670471",
        "href": "/670471/tbd-valorant-masters-london-2026-gf",
        "team1": "TBD",
        "team2": "TBD",
        "team1_logo": "/img/vlr/tmp/vlr.png",
        "team2_logo": "/img/vlr/tmp/vlr.png",
        "tournament": "Valorant Masters London 2026",
        "tournament_logo": "/static/images_cache/692fc18a04f4a.png",
        "series": "Playoffs–Grand Final",
        "unix_timestamp": 1782046800,
        "bst_time": "2026-06-21 07:00 PM",
        "status": "Upcoming",
        "score1": "–",
        "score2": "–",
        "last_updated": 1781716704
    },
    "688432": {
        "id": "688432",
        "href": "/688432/natus-vincere-junior-vs-be-ikta-esports-challengers-2026-emea-stage-3-opening-a",
        "team1": "Natus Vincere Junior",
        "team2": "Beşiktaş Esports",
        "team1_logo": "/static/images_cache/62a4109ddbd7f.png",
        "team2_logo": "/static/images_cache/623de5ba6273f.png",
        "tournament": "Challengers 2026: EMEA Stage 3",
        "tournament_logo": "/static/images_cache/6009f963577f4.png",
        "series": "Group Stage–Opening (A)",
        "unix_timestamp": 1782140400,
        "bst_time": "2026-06-22 09:00 PM",
        "status": "Upcoming",
        "score1": "–",
        "score2": "–",
        "last_updated": 1781716704
    },
    "688437": {
        "id": "688437",
        "href": "/688437/enterprise-esports-vs-bar-a-esports-challengers-2026-emea-stage-3-opening-b",
        "team1": "Enterprise Esports",
        "team2": "Barça eSports",
        "team1_logo": "/static/images_cache/68643d0b1c72b.png",
        "team2_logo": "/static/images_cache/65843488833d1.png",
        "tournament": "Challengers 2026: EMEA Stage 3",
        "tournament_logo": "/static/images_cache/6009f963577f4.png",
        "series": "Group Stage–Opening (B)",
        "unix_timestamp": 1782140400,
        "bst_time": "2026-06-22 09:00 PM",
        "status": "Upcoming",
        "score1": "–",
        "score2": "–",
        "last_updated": 1781716704
    },
    "688442": {
        "id": "688442",
        "href": "/688442/ucam-esports-club-vs-pixel-lumina-challengers-2026-emea-stage-3-opening-c",
        "team1": "UCAM Esports Club",
        "team2": "Pixel Lumina",
        "team1_logo": "/static/images_cache/5f7f77ef1e2f0.png",
        "team2_logo": "/static/images_cache/6783b1e6d26f8.png",
        "tournament": "Challengers 2026: EMEA Stage 3",
        "tournament_logo": "/static/images_cache/6009f963577f4.png",
        "series": "Group Stage–Opening (C)",
        "unix_timestamp": 1782149400,
        "bst_time": "2026-06-22 11:30 PM",
        "status": "Upcoming",
        "score1": "–",
        "score2": "–",
        "last_updated": 1781716704
    },
    "688447": {
        "id": "688447",
        "href": "/688447/reborn-vs-ghools-esports-challengers-2026-emea-stage-3-opening-d",
        "team1": "REBORN",
        "team2": "Ghools Esports",
        "team1_logo": "/static/images_cache/69d70973a1882.png",
        "team2_logo": "/static/images_cache/6989d854eb259.png",
        "tournament": "Challengers 2026: EMEA Stage 3",
        "tournament_logo": "/static/images_cache/6009f963577f4.png",
        "series": "Group Stage–Opening (D)",
        "unix_timestamp": 1782149400,
        "bst_time": "2026-06-22 11:30 PM",
        "status": "Upcoming",
        "score1": "–",
        "score2": "–",
        "last_updated": 1781716704
    },
    "676920": {
        "id": "676920",
        "href": "/676920/oxen-vs-leviat-n-academy-challengers-2026-latam-south-ace-stage-2-w5",
        "team1": "OXEN",
        "team2": "LEVIATÁN Academy",
        "team1_logo": "/static/images_cache/62cdc31a970d0.png",
        "team2_logo": "/static/images_cache/61b8888cc3860.png",
        "tournament": "Challengers 2026: LATAM South ACE Stage 2",
        "tournament_logo": "/static/images_cache/63cbac52cf906.png",
        "series": "Group Stage–Week 5",
        "unix_timestamp": 1782154800,
        "bst_time": "2026-06-23 01:00 AM",
        "status": "Upcoming",
        "score1": "–",
        "score2": "–",
        "last_updated": 1781716704
    },
    "676921": {
        "id": "676921",
        "href": "/676921/kr-blaze-vs-bestia-challengers-2026-latam-south-ace-stage-2-w5",
        "team1": "KRÜ BLAZE",
        "team2": "BESTIA",
        "team1_logo": "/static/images_cache/6704ad6a515a1.png",
        "team2_logo": "/static/images_cache/69ea66a9d008c.png",
        "tournament": "Challengers 2026: LATAM South ACE Stage 2",
        "tournament_logo": "/static/images_cache/63cbac52cf906.png",
        "series": "Group Stage–Week 5",
        "unix_timestamp": 1782165600,
        "bst_time": "2026-06-23 04:00 AM",
        "status": "Upcoming",
        "score1": "–",
        "score2": "–",
        "last_updated": 1781716704
    },
    "678058": {
        "id": "678058",
        "href": "/678058/ab3-esports-vs-chivas-esports-challengers-2026-latam-north-ace-stage-2-w5",
        "team1": "AB3 Esports",
        "team2": "Chivas Esports",
        "team1_logo": "/static/images_cache/679061092d445.png",
        "team2_logo": "/static/images_cache/63ce2eedbe573.png",
        "tournament": "Challengers 2026: LATAM North ACE Stage 2",
        "tournament_logo": "/static/images_cache/63cbac52cf906.png",
        "series": "Group Stage–Week 5",
        "unix_timestamp": 1782165600,
        "bst_time": "2026-06-23 04:00 AM",
        "status": "Upcoming",
        "score1": "–",
        "score2": "–",
        "last_updated": 1781716704
    },
    "678059": {
        "id": "678059",
        "href": "/678059/fusion-vs-lazer-challengers-2026-latam-north-ace-stage-2-w5",
        "team1": "FUSION",
        "team2": "LAZER",
        "team1_logo": "/static/images_cache/63bde15e27452.png",
        "team2_logo": "/static/images_cache/698051cea67f9.png",
        "tournament": "Challengers 2026: LATAM North ACE Stage 2",
        "tournament_logo": "/static/images_cache/63cbac52cf906.png",
        "series": "Group Stage–Week 5",
        "unix_timestamp": 1782176400,
        "bst_time": "2026-06-23 07:00 AM",
        "status": "Upcoming",
        "score1": "–",
        "score2": "–",
        "last_updated": 1781716704
    },
    "681796": {
        "id": "681796",
        "href": "/681796/reject-vs-qt-dig-challengers-2026-japan-split-2-w4",
        "team1": "REJECT",
        "team2": "QT DIG∞",
        "team1_logo": "/static/images_cache/62a4139de7f7e.png",
        "team2_logo": "/static/images_cache/67f4e2e7b3802.png",
        "tournament": "Challengers 2026: Japan Split 2",
        "tournament_logo": "/static/images_cache/6964a9e385d88.png",
        "series": "Main Stage–Week 4",
        "unix_timestamp": 1782198000,
        "bst_time": "2026-06-23 01:00 PM",
        "status": "Upcoming",
        "score1": "–",
        "score2": "–",
        "last_updated": 1781716704
    },
    "681797": {
        "id": "681797",
        "href": "/681797/crest-gaming-zst-vs-insomnia-challengers-2026-japan-split-2-w4",
        "team1": "CREST GAMING Zst",
        "team2": "Insomnia",
        "team1_logo": "/static/images_cache/63a33a790ae62.png",
        "team2_logo": "/static/images_cache/6a1be9015b7b5.png",
        "tournament": "Challengers 2026: Japan Split 2",
        "tournament_logo": "/static/images_cache/6964a9e385d88.png",
        "series": "Main Stage–Week 4",
        "unix_timestamp": 1782208800,
        "bst_time": "2026-06-23 04:00 PM",
        "status": "Upcoming",
        "score1": "–",
        "score2": "–",
        "last_updated": 1781716704
    },
    "688433": {
        "id": "688433",
        "href": "/688433/mandatory-vs-alqadsiah-esports-challengers-2026-emea-stage-3-opening-a",
        "team1": "Mandatory",
        "team2": "AlQadsiah Esports",
        "team1_logo": "/static/images_cache/695c961fbab82.png",
        "team2_logo": "/static/images_cache/672b6e5ef0749.png",
        "tournament": "Challengers 2026: EMEA Stage 3",
        "tournament_logo": "/static/images_cache/6009f963577f4.png",
        "series": "Group Stage–Opening (A)",
        "unix_timestamp": 1782226800,
        "bst_time": "2026-06-23 09:00 PM",
        "status": "Upcoming",
        "score1": "–",
        "score2": "–",
        "last_updated": 1781716704
    },
    "688438": {
        "id": "688438",
        "href": "/688438/joblife-vs-cgn-esports-challengers-2026-emea-stage-3-opening-b",
        "team1": "Joblife",
        "team2": "CGN Esports",
        "team1_logo": "/static/images_cache/63a944e6cbe49.png",
        "team2_logo": "/static/images_cache/60defafec983c.png",
        "tournament": "Challengers 2026: EMEA Stage 3",
        "tournament_logo": "/static/images_cache/6009f963577f4.png",
        "series": "Group Stage–Opening (B)",
        "unix_timestamp": 1782226800,
        "bst_time": "2026-06-23 09:00 PM",
        "status": "Upcoming",
        "score1": "–",
        "score2": "–",
        "last_updated": 1781716704
    },
    "688443": {
        "id": "688443",
        "href": "/688443/fokus-vs-mir-challengers-2026-emea-stage-3-opening-c",
        "team1": "FOKUS",
        "team2": "MIR",
        "team1_logo": "/static/images_cache/627934cd0b505.png",
        "team2_logo": "/static/images_cache/67dd7a34bc5d2.png",
        "tournament": "Challengers 2026: EMEA Stage 3",
        "tournament_logo": "/static/images_cache/6009f963577f4.png",
        "series": "Group Stage–Opening (C)",
        "unix_timestamp": 1782235800,
        "bst_time": "2026-06-23 11:30 PM",
        "status": "Upcoming",
        "score1": "–",
        "score2": "–",
        "last_updated": 1781716704
    },
    "688448": {
        "id": "688448",
        "href": "/688448/team-liquid-academy-vs-misa-esports-challengers-2026-emea-stage-3-opening-d",
        "team1": "Team Liquid Academy",
        "team2": "Misa Esports",
        "team1_logo": "/static/images_cache/640c381f0603f.png",
        "team2_logo": "/static/images_cache/6887b1d2edd20.png",
        "tournament": "Challengers 2026: EMEA Stage 3",
        "tournament_logo": "/static/images_cache/6009f963577f4.png",
        "series": "Group Stage–Opening (D)",
        "unix_timestamp": 1782235800,
        "bst_time": "2026-06-23 11:30 PM",
        "status": "Upcoming",
        "score1": "–",
        "score2": "–",
        "last_updated": 1781716704
    },
    "676922": {
        "id": "676922",
        "href": "/676922/kr-spark-vs-shinden-challengers-2026-latam-south-ace-stage-2-w5",
        "team1": "KRÜ SPARK",
        "team2": "ShindeN",
        "team1_logo": "/static/images_cache/69cfd386538cf.png",
        "team2_logo": "/static/images_cache/6748dec4df18c.png",
        "tournament": "Challengers 2026: LATAM South ACE Stage 2",
        "tournament_logo": "/static/images_cache/63cbac52cf906.png",
        "series": "Group Stage–Week 5",
        "unix_timestamp": 1782241200,
        "bst_time": "2026-06-24 01:00 AM",
        "status": "Upcoming",
        "score1": "–",
        "score2": "–",
        "last_updated": 1781716704
    },
    "676923": {
        "id": "676923",
        "href": "/676923/9z-globant-vs-university-war-challengers-2026-latam-south-ace-stage-2-w5",
        "team1": "9z Globant",
        "team2": "University War",
        "team1_logo": "/static/images_cache/65e447b0c2415.png",
        "team2_logo": "/static/images_cache/65df25f7afcad.png",
        "tournament": "Challengers 2026: LATAM South ACE Stage 2",
        "tournament_logo": "/static/images_cache/63cbac52cf906.png",
        "series": "Group Stage–Week 5",
        "unix_timestamp": 1782252000,
        "bst_time": "2026-06-24 04:00 AM",
        "status": "Upcoming",
        "score1": "–",
        "score2": "–",
        "last_updated": 1781716704
    }
}